{
  "project_info": {
    "project_number": "268222305008",
    "project_id": "cryptocurrency-price-tra-d3fc6",
    "storage_bucket": "cryptocurrency-price-tra-d3fc6.appspot.com"
  },
  "client": [
    {
      "client_info": {
        "mobilesdk_app_id": "1:268222305008:android:98f15db1b1e46007b66835",
        "android_client_info": {
          "package_name": "com.mertdev.cryptocurrencypricetracker"
        }
      },
      "oauth_client": [
        {
          "client_id": "268222305008-0kvn6von38pvru57lnpflrp3hdge3ajl.apps.googleusercontent.com",
          "client_type": 3
        }
      ],
      "api_key": [
        {
          "current_key": "AIzaSyBrnXH3s5Oc0rE1PWeOo9sbMoiKL0pgxzI"
        }
      ],
      "services": {
        "appinvite_service": {
          "other_platform_oauth_client": [
            {
              "client_id": "268222305008-0kvn6von38pvru57lnpflrp3hdge3ajl.apps.googleusercontent.com",
              "client_type": 3
            }
          ]
        }
      }
    }
  ],
  "configuration_version": "1"
}